gpmf/__init__.py
gpmf/__main__.py
gpmf/gps.py
gpmf/gps_plot.py
gpmf/io.py
gpmf/parse.py
pygpmf/__init__.py
pygpmf/__main__.py
pygpmf/gps.py
pygpmf/gps_plot.py
pygpmf/io.py
pygpmf/parse.py
gpmf-0.1.dist-info/LICENSE
gpmf-0.1.dist-info/METADATA
gpmf-0.1.dist-info/WHEEL
gpmf-0.1.dist-info/top_level.txt
gpmf-0.1.dist-info/RECORD
