Metadata-Version: 2.1
Name: gpmf
Version: 0.1
Summary: A module to read GPMF data embedded in GoPro video files.
Home-page: https://github.com/alexis-mignon/pygpmf
Author: Alexis Mignon
Author-email: alexis.mignon@gmail.com
License: UNKNOWN
Platform: UNKNOWN
Requires-Dist: numpy
Requires-Dist: pandas
Requires-Dist: gpxpy
Requires-Dist: python-ffmpeg
Requires-Dist: geopandas
Requires-Dist: contextily
Requires-Dist: descartes
